aletheion_guard/__init__.py
aletheion_guard/api.py
aletheion_guard/api_proxy.py
aletheion_guard/auditor.py
aletheion_guard/cli.py
aletheion_guard/config.py
aletheion_guard/epistemic_softmax.py
aletheion_guard/input_processor.py
aletheion_guard/logging_config.py
aletheion_guard/metrics.py
aletheion_guard/pyramidal.py
aletheion_guard/q1q2_gates.py
aletheion_guard/security.py
aletheion_guard/tracing_config.py
aletheion_guard/models/__init__.py
aletheion_guard/models/base_forces.pth
aletheion_guard/models/height_gate.pth
aletheion_guard/models/q1_gate.pth
aletheion_guard/models/q2_gate.pth
aletheion_guard-1.1.2.dist-info/licenses/LICENSE.md
aletheion_guard-1.1.2.dist-info/licenses/NOTICE
utils/__init__.py
utils/calibration.py
utils/metrics.py
aletheion_guard-1.1.2.dist-info/METADATA
aletheion_guard-1.1.2.dist-info/WHEEL
aletheion_guard-1.1.2.dist-info/entry_points.txt
aletheion_guard-1.1.2.dist-info/top_level.txt
aletheion_guard-1.1.2.dist-info/RECORD
