Metadata-Version: 2.4
Name: aletheion-guard
Version: 1.1.2
Summary: Epistemic auditor for LLM outputs - quantifies uncertainty to detect hallucinations
Author-email: Aletheion Research Collective <contact@aletheionagi.com>
Maintainer-email: Felipe Maya Muniz <contact@aletheionagi.com>
License: AGPL-3.0-or-later
Project-URL: Homepage, https://aletheionguard.com
Project-URL: Documentation, https://aletheionguard.com/docs
Project-URL: Repository, https://github.com/AletheionAGI/AletheionGuard-Pypi
Project-URL: Bug Tracker, https://github.com/AletheionAGI/AletheionGuard-Pypi/issues
Project-URL: Changelog, https://github.com/AletheionAGI/AletheionGuard-Pypi/blob/main/CHANGELOG.md
Keywords: llm,uncertainty,calibration,epistemic,aleatoric,hallucination-detection,ai-safety,machine-learning,deep-learning,pytorch
Classifier: Development Status :: 4 - Beta
Classifier: Intended Audience :: Developers
Classifier: Intended Audience :: Science/Research
Classifier: License :: OSI Approved :: GNU Affero General Public License v3
Classifier: Operating System :: OS Independent
Classifier: Programming Language :: Python :: 3
Classifier: Programming Language :: Python :: 3.8
Classifier: Programming Language :: Python :: 3.9
Classifier: Programming Language :: Python :: 3.10
Classifier: Programming Language :: Python :: 3.11
Classifier: Programming Language :: Python :: 3.12
Classifier: Topic :: Scientific/Engineering :: Artificial Intelligence
Classifier: Topic :: Software Development :: Libraries :: Python Modules
Classifier: Typing :: Typed
Requires-Python: >=3.8
License-File: LICENSE.md
License-File: NOTICE
Requires-Dist: torch>=2.0.0
Requires-Dist: transformers>=4.30.0
Requires-Dist: sentence-transformers>=2.2.0
Requires-Dist: numpy>=1.24.0
Requires-Dist: scipy>=1.10.0
Requires-Dist: tqdm>=4.65.0
Requires-Dist: pydantic>=2.0.0
Provides-Extra: api
Requires-Dist: fastapi>=0.100.0; extra == "api"
Requires-Dist: uvicorn[standard]>=0.23.0; extra == "api"
Requires-Dist: pydantic-settings>=2.0.0; extra == "api"
Requires-Dist: httpx>=0.24.0; extra == "api"
Requires-Dist: slowapi>=0.1.9; extra == "api"
Requires-Dist: redis>=5.0.0; extra == "api"
Provides-Extra: monitoring
Requires-Dist: prometheus-client>=0.19.0; extra == "monitoring"
Requires-Dist: prometheus-fastapi-instrumentator>=7.0.0; extra == "monitoring"
Requires-Dist: opentelemetry-api>=1.20.0; extra == "monitoring"
Requires-Dist: opentelemetry-sdk>=1.20.0; extra == "monitoring"
Requires-Dist: opentelemetry-instrumentation-fastapi>=0.41b0; extra == "monitoring"
Requires-Dist: opentelemetry-exporter-jaeger>=1.20.0; extra == "monitoring"
Requires-Dist: opentelemetry-exporter-otlp>=1.20.0; extra == "monitoring"
Requires-Dist: structlog>=24.1.0; extra == "monitoring"
Requires-Dist: python-json-logger>=2.0.0; extra == "monitoring"
Provides-Extra: ml
Requires-Dist: pytorch-lightning>=2.0.0; extra == "ml"
Requires-Dist: optuna>=3.0.0; extra == "ml"
Requires-Dist: scikit-learn>=1.3.0; extra == "ml"
Requires-Dist: pandas>=2.0.0; extra == "ml"
Provides-Extra: viz
Requires-Dist: matplotlib>=3.7.0; extra == "viz"
Requires-Dist: seaborn>=0.12.0; extra == "viz"
Requires-Dist: tensorboard>=2.13.0; extra == "viz"
Provides-Extra: tracking
Requires-Dist: wandb>=0.15.0; extra == "tracking"
Provides-Extra: dev
Requires-Dist: pytest>=7.4.0; extra == "dev"
Requires-Dist: pytest-asyncio>=0.21.0; extra == "dev"
Requires-Dist: pytest-cov>=4.1.0; extra == "dev"
Requires-Dist: black>=23.7.0; extra == "dev"
Requires-Dist: flake8>=6.0.0; extra == "dev"
Requires-Dist: mypy>=1.4.0; extra == "dev"
Requires-Dist: isort>=5.12.0; extra == "dev"
Requires-Dist: pre-commit>=3.3.0; extra == "dev"
Provides-Extra: docs
Requires-Dist: mkdocs>=1.5.0; extra == "docs"
Requires-Dist: mkdocs-material>=9.1.0; extra == "docs"
Requires-Dist: mkdocstrings[python]>=0.22.0; extra == "docs"
Provides-Extra: all
Requires-Dist: aletheion-guard[api,ml,monitoring,tracking,viz]; extra == "all"
Provides-Extra: full
Requires-Dist: aletheion-guard[all,dev,docs]; extra == "full"
Dynamic: license-file
